README.md
setup.py
venvlink/__init__.py
venvlink/__main__.py
venvlink/__version__.py
venvlink/config.py
venvlink/exceptions.py
venvlink/utils.py
venvlink.egg-info/PKG-INFO
venvlink.egg-info/SOURCES.txt
venvlink.egg-info/dependency_links.txt
venvlink.egg-info/top_level.txt