Metadata-Version: 2.1
Name: venvlink
Version: 0.5.0
Summary: Creating the virtual environment outside of the project folder, still retaining the feel of good ol' "python -m venv venv".
Home-page: https://github.com/np-8/venvlink
Author: Niko Pasanen
Author-email: niko@pasanen.me
License: MIT
Platform: UNKNOWN
Classifier: Intended Audience :: Developers
Classifier: License :: OSI Approved :: MIT License
Classifier: Topic :: Utilities
